odoo/addons/pos_order_count_store/README.rst
odoo/addons/pos_order_count_store/__init__.py
odoo/addons/pos_order_count_store/__manifest__.py
odoo/addons/pos_order_count_store/pre_init_hook.py
odoo/addons/pos_order_count_store/i18n/it.po
odoo/addons/pos_order_count_store/i18n/pos_order_count_store.pot
odoo/addons/pos_order_count_store/models/__init__.py
odoo/addons/pos_order_count_store/models/res_partner.py
odoo/addons/pos_order_count_store/readme/CONTRIBUTORS.rst
odoo/addons/pos_order_count_store/readme/DESCRIPTION.rst
odoo/addons/pos_order_count_store/static/description/icon.png
odoo/addons/pos_order_count_store/static/description/index.html
odoo12_addon_pos_order_count_store-12.0.1.0.0.99.dev7.dist-info/METADATA
odoo12_addon_pos_order_count_store-12.0.1.0.0.99.dev7.dist-info/WHEEL
odoo12_addon_pos_order_count_store-12.0.1.0.0.99.dev7.dist-info/top_level.txt
odoo12_addon_pos_order_count_store-12.0.1.0.0.99.dev7.dist-info/RECORD
